odoo10_addon_stock_picking_show_return-10.0.1.0.0-py2.7-nspkg.pth
odoo/addons/stock_picking_show_return/README.rst
odoo/addons/stock_picking_show_return/__init__.py
odoo/addons/stock_picking_show_return/__manifest__.py
odoo/addons/stock_picking_show_return/i18n/de.po
odoo/addons/stock_picking_show_return/i18n/es.po
odoo/addons/stock_picking_show_return/i18n/fr.po
odoo/addons/stock_picking_show_return/i18n/it.po
odoo/addons/stock_picking_show_return/i18n/pt_BR.po
odoo/addons/stock_picking_show_return/i18n/sl.po
odoo/addons/stock_picking_show_return/i18n/stock_picking_show_returns.pot
odoo/addons/stock_picking_show_return/i18n/stock_picking_update_date.pot
odoo/addons/stock_picking_show_return/models/__init__.py
odoo/addons/stock_picking_show_return/models/stock_picking.py
odoo/addons/stock_picking_show_return/tests/__init__.py
odoo/addons/stock_picking_show_return/tests/test_stock_picking_show_return.py
odoo/addons/stock_picking_show_return/views/stock_picking_view.xml
odoo10_addon_stock_picking_show_return-10.0.1.0.0.dist-info/DESCRIPTION.rst
odoo10_addon_stock_picking_show_return-10.0.1.0.0.dist-info/METADATA
odoo10_addon_stock_picking_show_return-10.0.1.0.0.dist-info/RECORD
odoo10_addon_stock_picking_show_return-10.0.1.0.0.dist-info/WHEEL
odoo10_addon_stock_picking_show_return-10.0.1.0.0.dist-info/metadata.json
odoo10_addon_stock_picking_show_return-10.0.1.0.0.dist-info/namespace_packages.txt
odoo10_addon_stock_picking_show_return-10.0.1.0.0.dist-info/top_level.txt
